README.md
setup.py
wypy/__init__.py
wypy/cli.py
wypy/wypy.py
wypy.egg-info/PKG-INFO
wypy.egg-info/SOURCES.txt
wypy.egg-info/dependency_links.txt
wypy.egg-info/entry_points.txt
wypy.egg-info/requires.txt
wypy.egg-info/top_level.txt
wypy/connection/__init__.py
wypy/connection/commands.py
wypy/connection/connection.py
wypy/device/__init__.py
wypy/device/commands.py
wypy/device/device.py
wypy/general/__init__.py
wypy/general/commands.py
wypy/general/general.py
wypy/networking/__init__.py
wypy/networking/commands.py
wypy/networking/networking.py
wypy/tests/__init__.py
wypy/tests/conftest.py
wypy/tests/test_connection.py
wypy/tests/test_device.py
wypy/tests/test_general.py
wypy/tests/test_helpers.py
wypy/tests/test_networking.py
wypy/tests/test_wifi.py
wypy/tests/test_wypy.py
wypy/tests/cli/__init__.py
wypy/tests/cli/test_cli.py
wypy/utils/__init__.py
wypy/utils/constants.py
wypy/utils/helpers.py
wypy/wifi/__init__.py
wypy/wifi/commands.py
wypy/wifi/wifi.py