Metadata-Version: 2.1
Name: wypy
Version: 1.0.0
Summary: A NetworkManager CLI utility.
Home-page: https://github.com/Zabanaa/wypy
Author: Karim C
Author-email: karim.cheurfi@gmail.com
License: UNKNOWN
Keywords: network-manager network manager nmcli dbus d-bus
Platform: UNKNOWN
Classifier: Development Status :: 5 - Production/Stable
Classifier: Programming Language :: Python :: 3.7
Classifier: Programming Language :: Python :: 3.8
Classifier: Intended Audience :: Developers
Classifier: Operating System :: OS Independent
Classifier: Topic :: Security
Requires-Python: >=3.7
